spacepackets/__init__.py
spacepackets/countdown.py
spacepackets/crc.py
spacepackets/exceptions.py
spacepackets/seqcount.py
spacepackets/util.py
spacepackets/version.py
spacepackets/ccsds/__init__.py
spacepackets/ccsds/spacepacket.py
spacepackets/ccsds/tm_frame.py
spacepackets/ccsds/time/__init__.py
spacepackets/ccsds/time/cds.py
spacepackets/ccsds/time/common.py
spacepackets/cfdp/__init__.py
spacepackets/cfdp/conf.py
spacepackets/cfdp/defs.py
spacepackets/cfdp/lv.py
spacepackets/cfdp/pdu/__init__.py
spacepackets/cfdp/pdu/ack.py
spacepackets/cfdp/pdu/eof.py
spacepackets/cfdp/pdu/file_data.py
spacepackets/cfdp/pdu/file_directive.py
spacepackets/cfdp/pdu/finished.py
spacepackets/cfdp/pdu/header.py
spacepackets/cfdp/pdu/helper.py
spacepackets/cfdp/pdu/keep_alive.py
spacepackets/cfdp/pdu/metadata.py
spacepackets/cfdp/pdu/nak.py
spacepackets/cfdp/pdu/prompt.py
spacepackets/cfdp/tlv/__init__.py
spacepackets/cfdp/tlv/base.py
spacepackets/cfdp/tlv/defs.py
spacepackets/cfdp/tlv/holder.py
spacepackets/cfdp/tlv/msg_to_user.py
spacepackets/cfdp/tlv/tlv.py
spacepackets/ecss/__init__.py
spacepackets/ecss/defs.py
spacepackets/ecss/exceptions.py
spacepackets/ecss/fields.py
spacepackets/ecss/pus_15_tm_storage.py
spacepackets/ecss/pus_17_test.py
spacepackets/ecss/pus_1_verification.py
spacepackets/ecss/pus_3_hk.py
spacepackets/ecss/pus_5_event.py
spacepackets/ecss/pus_verificator.py
spacepackets/ecss/req_id.py
spacepackets/ecss/tc.py
spacepackets/ecss/tm.py
spacepackets/uslp/__init__.py
spacepackets/uslp/defs.py
spacepackets/uslp/frame.py
spacepackets/uslp/header.py
spacepackets-0.30.1.dist-info/licenses/LICENSE
spacepackets-0.30.1.dist-info/licenses/NOTICE
spacepackets-0.30.1.dist-info/METADATA
spacepackets-0.30.1.dist-info/WHEEL
spacepackets-0.30.1.dist-info/top_level.txt
spacepackets-0.30.1.dist-info/RECORD
