Metadata-Version: 2.4
Name: spacepackets
Version: 0.30.1
Summary: Various CCSDS and ECSS packet implementations
Author-email: Robin Mueller <robin.mueller.m@gmail.com>
License: Apache-2.0
Project-URL: Homepage, https://github.com/us-irs/spacepackets-py
Keywords: ccsds,ecss,space,communication,packet
Classifier: Development Status :: 5 - Production/Stable
Classifier: License :: OSI Approved :: Apache Software License
Classifier: Natural Language :: English
Classifier: Operating System :: POSIX
Classifier: Operating System :: Microsoft :: Windows
Classifier: Programming Language :: Python :: 3
Classifier: Programming Language :: Python :: 3.8
Classifier: Programming Language :: Python :: 3.9
Classifier: Topic :: Communications
Classifier: Topic :: Software Development :: Libraries
Classifier: Topic :: Software Development :: Libraries :: Python Modules
Classifier: Topic :: Scientific/Engineering
Requires-Python: >=3.9
License-File: LICENSE
License-File: NOTICE
Requires-Dist: fastcrc~=0.3.0
Requires-Dist: deprecation~=2.1
Dynamic: license-file
